ai/__init__.py
ai/api.py
ai/cluster_spec.py
ai/config.py
ai/jobfile.py
ai/main.py
ai/provider_spec.py
codedepot_ai-0.1.5.dist-info/METADATA
codedepot_ai-0.1.5.dist-info/WHEEL
codedepot_ai-0.1.5.dist-info/entry_points.txt
test/__init__.py
test/resources/cluster_test.yaml
test/resources/config.json
test/resources/local_cred.json
test/resources/provider_test.yaml
test/test_client.py
test/test_provider.py
test/utils.py
codedepot_ai-0.1.5.dist-info/RECORD
